pandas_bokeh/__init__.py
pandas_bokeh/base.py
pandas_bokeh/geoplot.py
pandas_bokeh/plot.py
pandas_bokeh-0.5.5.dist-info/LICENSE
pandas_bokeh-0.5.5.dist-info/METADATA
pandas_bokeh-0.5.5.dist-info/WHEEL
pandas_bokeh-0.5.5.dist-info/top_level.txt
pandas_bokeh-0.5.5.dist-info/RECORD
