Metadata-Version: 2.1
Name: pandas-bokeh
Version: 0.5.5
Summary: Bokeh plotting backend for Pandas, GeoPandas & Pyspark
Home-page: https://github.com/PatrikHlobil/Pandas-Bokeh
Author: Patrik Hlobil
Author-email: patrik.hlobil@googlemail.com
License: UNKNOWN
Platform: UNKNOWN
Classifier: Programming Language :: Python :: 3.6
Classifier: Programming Language :: Python :: 3.7
Classifier: Programming Language :: Python :: 3.8
Classifier: License :: OSI Approved :: MIT License
Classifier: Operating System :: OS Independent
Classifier: Intended Audience :: Science/Research
Classifier: Topic :: Scientific/Engineering
Classifier: Topic :: Scientific/Engineering :: Visualization
Requires-Python: >=3.6
